{
    "type": "Feature",
    "stac_version": "1.0.0",
    "stac_extensions": [],
    "id": "ukcp.land-rcm.uk.12km.rcp85.15.sfcWind.day.v20190731",
    "collection": "ukcp",
    "geometry": {
        "coordinates": [
            [
                [
                    -8.18,
                    49.86
                ],
                [
                    -8.18,
                    60.86
                ],
                [
                    1.76,
                    60.86
                ],
                [
                    1.76,
                    49.86
                ],
                [
                    -8.18,
                    49.86
                ]
            ]
        ],
        "type": "Polygon"
    },
    "bbox": [
        49.86,
        -8.18,
        60.86,
        1.76
    ],
    "properties": {
        "file_count": 2,
        "Conventions": "CF-1.5",
        "references": "https://ukclimateprojections.metoffice.gov.uk",
        "start_datetime": "2060-12-01T12:00:00Z",
        "end_datetime": "2080-11-30T12:00:00Z",
        "sub_collection": "land-rcm",
        "variable_long_name": "Wind speed at 10m",
        "created": "2024-01-29T12:02:16.353442Z",
        "dataset_id": "ukcp.land-rcm.uk.12km.rcp85.15.sfcWind.day.v20190731",
        "variable_units": "m s-1",
        "project": "UKCP18",
        "cf_standard_name": "wind_speed",
        "kerchunk_href": "https://dap.ceda.ac.uk/badc/cmip18/metadata/kerchunk/by_dset/UKCP/land-rcm/uk/12km/rcp85/sfcWind/day/ukcp.land-rcm.uk.12km.rcp85.15.sfcWind.day.v20190731.zstd",
        "resolution": "12km",
        "version": "v20190731",
        "frequency": "day",
        "institution": "Met Office Hadley Centre (MOHC), FitzRoy Road, Exeter, Devon, EX1 3PB, UK.",
        "datetime": "2070-12-01T12:00:00Z",
        "size": 266750246,
        "scenario": "rcp85",
        "domain": "uk",
        "var_id": "sfcWind",
        "updated": "2024-01-29T12:02:16.353442Z",
        "latest": true
    },
    "links": [
        {
            "rel": "self",
            "type": "application/geo+json",
            "href": "https://dev.eodatahub.org.uk/catalogue-data/supported/collections/ukcp/items/ukcp.land-rcm.uk.12km.rcp85.15.sfcWind.day.v20190731.json"
        },
        {
            "rel": "parent",
            "type": "application/json",
            "href": "https://dev.eodatahub.org.uk/catalogue-data/supported/collections/ukcp.json"
        },
        {
            "rel": "collection",
            "type": "application/json",
            "href": "https://dev.eodatahub.org.uk/catalogue-data/supported/collections/ukcp.json"
        },
        {
            "rel": "root",
            "type": "application/json",
            "href": "https://dev.eodatahub.org.uk/catalogue-data/supported/catalog.json"
        }
    ],
    "assets": {
        "reference_file": {
            "checksum_type": null,
            "size": null,
            "open_zarr_kwargs": {
                "decode_times": true
            },
            "roles": [
                "reference",
                "data"
            ],
            "checksum": null,
            "href": "https://dap.ceda.ac.uk/badc/cmip18/metadata/kerchunk/by_dset/UKCP/land-rcm/uk/12km/rcp85/sfcWind/day/ukcp.land-rcm.uk.12km.rcp85.15.sfcWind.day.v20190731.zstd",
            "type": "application/zstd"
        },
        "data0001": {
            "checksum_type": null,
            "size": 133375123,
            "start_datetime": "2060-12-01T00:00:00",
            "end_datetime": "2070-11-30T23:59:59",
            "roles": [
                "data"
            ],
            "bbox": [
                -18.24145632530888,
                -0.8710618968191547,
                -6.580251255557555,
                12.94984143216418
            ],
            "checksum": null,
            "location": "on_disk",
            "href": "https://dap.ceda.ac.uk/badc/ukcp18/data/land-rcm/uk/12km/rcp85/15/sfcWind/day/v20190731/sfcWind_rcp85_land-rcm_uk_12km_15_day_20601201-20701130.nc",
            "type": "application/netcdf"
        },
        "data0002": {
            "checksum_type": null,
            "size": 133375123,
            "start_datetime": "2070-12-01T00:00:00",
            "end_datetime": "2080-11-30T23:59:59",
            "roles": [
                "data"
            ],
            "bbox": [
                -18.24145632530888,
                -0.8710618968191547,
                -6.580251255557555,
                12.94984143216418
            ],
            "checksum": null,
            "location": "on_disk",
            "href": "https://dap.ceda.ac.uk/badc/ukcp18/data/land-rcm/uk/12km/rcp85/15/sfcWind/day/v20190731/sfcWind_rcp85_land-rcm_uk_12km_15_day_20701201-20801130.nc",
            "type": "application/netcdf"
        }
    }
}